talvez/__init__.py
talvez/core.py
talvez/ops.py
talvez/predicates.py
talvez/wrappers.py
talvez-0.0.9.dist-info/licenses/LICENSE.md
talvez-0.0.9.dist-info/METADATA
talvez-0.0.9.dist-info/WHEEL
talvez-0.0.9.dist-info/top_level.txt
talvez-0.0.9.dist-info/RECORD
