Metadata-Version: 2.4
Name: talvez
Version: 0.0.9
Summary: A lightweight Python implementation of a Maybe monad
Author: Bruno Rodrigues
License: GPL-3.0-or-later
Project-URL: Homepage, https://github.com/b-rodrigues/talvez
Project-URL: Bug Tracker, https://github.com/b-rodrigues/talvez/issues
Keywords: maybe,functional programming
Classifier: Programming Language :: Python :: 3
Classifier: Operating System :: OS Independent
Requires-Python: >=3.8
License-File: LICENSE.md
Provides-Extra: dev
Requires-Dist: pytest>=7.0; extra == "dev"
Requires-Dist: numpy; extra == "dev"
Dynamic: license-file
